{"HEADER": {"CompID": "115", "competition": "PRIMERA FEB", "round": "Único               ", "quarter": 4, "time": "FINAL", "logo": null, "duration": null, "starttime": "01-11-2025 - 19:00", "place": "FINCA SEVILLA, S/N, Ourense (Ourense)", "field": "PAZO DOS DEPORTES PACO PAZ", "referee1": "DE LUCAS DE LUCAS, ANGEL", "referee2": "CAAMAÑO MUÑOZ, JORGE", "referee3": "FANES MARGINET, JOAN", "status": "3", "statusText": "FINISHED", "TEAM": [{"pts": "84", "fouls": null, "id": "981493", "name": "CLUB OURENSE BALONCESTO", "logo": "https://imagenes.feb.es/imagen.aspx?i=981493&ti=1", "teamCode": "32000100", "clubCode": "320001"}, {"pts": "80", "fouls": null, "id": "981300", "name": "HESTIA MENORCA", "logo": "https://imagenes.feb.es/imagen.aspx?i=981300&ti=1", "teamCode": "07033323", "clubCode": "070333"}], "QUARTERS": {"QUARTER": [{"n": "1", "scoreA": "23", "scoreB": "20"}, {"n": "2", "scoreA": "26", "scoreB": "19"}, {"n": "3", "scoreA": "18", "scoreB": "18"}, {"n": "4", "scoreA": "17", "scoreB": "23"}]}}, "SCOREBOARD": null, "TEAMSTATS": null, "TICKER": {"text": null, "duration": null, "ITEM": null}, "OVERVIEW": null, "PLAYBYPLAY": null, "BANNER": null, "BOXSCORE": {"duration": null, "TEAM": [{"TOTAL": {"p1m": "13", "p1a": "25", "p1p": "52,0", "p2m": "25", "p2a": "45", "p2p": "55,6", "p3m": "7", "p3a": "17", "p3p": "41,2", "fgm": "32", "fga": "62", "fgp": "51,6", "assist": "18", "bs": "5", "tc": "1", "mt": "3", "ro": "14", "rd": "21", "rt": "35", "pf": "23", "rf": "23", "to": "13", "st": "6", "fastb": null, "ptsto": null, "secpts": null, "bench": null, "paint": null, "min": "12000", "minFormatted": "200:00", "val": "93", "pts": "84", "fouls": "23", "id": "981493", "name": "CLUB OURENSE BALONCESTO", "logo": "https://imagenes.feb.es/imagen.aspx?i=981493&ti=1", "teamCode": "32000100", "clubCode": "320001"}, "TEAMACTIONS": {"p1m": null, "p1a": null, "p1p": "0,0", "p2m": null, "p2a": null, "p2p": "0,0", "p3m": null, "p3a": null, "p3p": "0,0", "fgm": "0", "fga": "0", "fgp": "0,0", "assist": null, "bs": null, "tc": null, "mt": null, "ro": "14", "rd": "21", "rt": "35", "pf": "23", "rf": "23", "to": "13", "st": "6", "fastb": null, "ptsto": null, "secpts": null, "bench": null, "paint": null, "min": null, "minFormatted": "0:00", "val": null, "pts": null, "fouls": "23", "id": "981493", "name": "CLUB OURENSE BALONCESTO", "logo": "https://imagenes.feb.es/imagen.aspx?i=981493&ti=1", "teamCode": "32000100", "clubCode": "320001"}, "PLAYER": [{"p1m": "0", "p1a": "2", "p1p": "0,0", "p2m": "2", "p2a": "6", "p2p": "33,3", "p3m": "2", "p3a": "2", "p3p": "100,0", "fgm": "4", "fga": "8", "fgp": "50,0", "min": "1411", "minFormatted": "23:31", "sta": null, "bs": "1", "tc": "0", "mt": "2", "ro": "2", "rd": "3", "rt": "5", "rf": "1", "to": "2", "st": "0", "ind": null, "pllss": "13", "val": "11", "assist": "2", "reb": "5", "pf": "0", "pts": "10", "inn": "0", "captain": "0", "id": "2819338", "no": "3", "name": "K. SMITH", "logo": "https://imagenes.feb.es/foto.aspx?c=2819338"}, {"p1m": "3", "p1a": "7", "p1p": "42,9", "p2m": "3", "p2a": "4", "p2p": "75,0", "p3m": "0", "p3a": "0", "p3p": "0,0", "fgm": "3", "fga": "4", "fgp": "75,0", "min": "832", "minFormatted": "13:52", "sta": null, "bs": "0", "tc": "0", "mt": "0", "ro": "1", "rd": "3", "rt": "4", "rf": "7", "to": "0", "st": "0", "ind": null, "pllss": "-5", "val": "12", "assist": "0", "reb": "4", "pf": "3", "pts": "9", "inn": "0", "captain": "0", "id": "2819330", "no": "9", "name": "C. OKANU", "logo": "https://imagenes.feb.es/foto.aspx?c=2819330"}, {"p1m": "0", "p1a": "0", "p1p": "0,0", "p2m": "5", "p2a": "6", "p2p": "83,3", "p3m": "0", "p3a": "2", "p3p": "0,0", "fgm": "5", "fga": "8", "fgp": "62,5", "min": "1316", "minFormatted": "21:56", "sta": null, "bs": "0", "tc": "0", "mt": "0", "ro": "0", "rd": "4", "rt": "4", "rf": "1", "to": "3", "st": "1", "ind": null, "pllss": "-10", "val": "11", "assist": "5", "reb": "4", "pf": "4", "pts": "10", "inn": "0", "captain": "0", "id": "1778999", "no": "10", "name": "I. VAZQUEZ PEREZ", "logo": "https://imagenes.feb.es/foto.aspx?c=1778999"}, {"p1m": "1", "p1a": "2", "p1p": "50,0", "p2m": "1", "p2a": "3", "p2p": "33,3", "p3m": "0", "p3a": "1", "p3p": "0,0", "fgm": "1", "fga": "4", "fgp": "25,0", "min": "364", "minFormatted": "06:04", "sta": null, "bs": "0", "tc": "0", "mt": "0", "ro": "0", "rd": "0", "rt": "0", "rf": "1", "to": "0", "st": "0", "ind": null, "pllss": "-2", "val": "-1", "assist": "0", "reb": "0", "pf": "1", "pts": "3", "inn": "0", "captain": "0", "id": "1886852", "no": "11", "name": "M. FERNANDEZ CARBALLO", "logo": "https://imagenes.feb.es/foto.aspx?c=1886852"}, {"p1m": "0", "p1a": "0", "p1p": "0,0", "p2m": "1", "p2a": "2", "p2p": "50,0", "p3m": "0", "p3a": "2", "p3p": "0,0", "fgm": "1", "fga": "4", "fgp": "25,0", "min": "767", "minFormatted": "12:47", "sta": null, "bs": "0", "tc": "0", "mt": "0", "ro": "1", "rd": "0", "rt": "1", "rf": "0", "to": "0", "st": "0", "ind": null, "pllss": "-1", "val": "2", "assist": "2", "reb": "1", "pf": "0", "pts": "2", "inn": "0", "captain": "0", "id": "1765084", "no": "12", "name": "S. HUGUET CARRASCO", "logo": "https://imagenes.feb.es/foto.aspx?c=1765084"}, {"p1m": "5", "p1a": "6", "p1p": "83,3", "p2m": "3", "p2a": "5", "p2p": "60,0", "p3m": "2", "p3a": "5", "p3p": "40,0", "fgm": "5", "fga": "10", "fgp": "50,0", "min": "1785", "minFormatted": "29:45", "sta": null, "bs": "0", "tc": "0", "mt": "0", "ro": "0", "rd": "1", "rt": "1", "rf": "6", "to": "1", "st": "2", "ind": null, "pllss": "6", "val": "20", "assist": "4", "reb": "1", "pf": "3", "pts": "17", "inn": "1", "captain": "0", "id": "2819327", "no": "22", "name": "G. KALSCHEUR", "logo": "https://imagenes.feb.es/foto.aspx?c=2819327"}, {"p1m": "0", "p1a": "0", "p1p": "0,0", "p2m": "0", "p2a": "0", "p2p": "0,0", "p3m": "0", "p3a": "0", "p3p": "0,0", "fgm": "0", "fga": "0", "fgp": "0,0", "min": "6", "minFormatted": "00:06", "sta": null, "bs": "0", "tc": "0", "mt": "0", "ro": "0", "rd": "0", "rt": "0", "rf": "0", "to": "0", "st": "0", "ind": null, "pllss": "0", "val": "0", "assist": "0", "reb": "0", "pf": "0", "pts": "0", "inn": "0", "captain": "0", "id": "2819332", "no": "23", "name": "D. SARAIVA SEIXAS", "logo": "https://imagenes.feb.es/foto.aspx?c=2819332"}, {"p1m": "1", "p1a": "2", "p1p": "50,0", "p2m": "0", "p2a": "2", "p2p": "0,0", "p3m": "1", "p3a": "2", "p3p": "50,0", "fgm": "1", "fga": "4", "fgp": "25,0", "min": "1795", "minFormatted": "29:55", "sta": null, "bs": "0", "tc": "0", "mt": "0", "ro": "0", "rd": "2", "rt": "2", "rf": "2", "to": "2", "st": "0", "ind": null, "pllss": "-7", "val": "3", "assist": "2", "reb": "2", "pf": "1", "pts": "4", "inn": "1", "captain": "0", "id": "2781800", "no": "24", "name": "S. MC DONNELL", "logo": "https://imagenes.feb.es/foto.aspx?c=2781800"}, {"p1m": "0", "p1a": "0", "p1p": "0,0", "p2m": "3", "p2a": "7", "p2p": "42,9", "p3m": "0", "p3a": "0", "p3p": "0,0", "fgm": "3", "fga": "7", "fgp": "42,9", "min": "770", "minFormatted": "12:50", "sta": null, "bs": "0", "tc": "0", "mt": "0", "ro": "4", "rd": "1", "rt": "5", "rf": "1", "to": "0", "st": "0", "ind": null, "pllss": "9", "val": "8", "assist": "1", "reb": "5", "pf": "1", "pts": "6", "inn": "0", "captain": "0", "id": "1863291", "no": "27", "name": "M. IGLESIAS FERNANDEZ", "logo": "https://imagenes.feb.es/foto.aspx?c=1863291"}, {"p1m": "3", "p1a": "4", "p1p": "75,0", "p2m": "3", "p2a": "5", "p2p": "60,0", "p3m": "2", "p3a": "2", "p3p": "100,0", "fgm": "5", "fga": "7", "fgp": "71,4", "min": "1251", "minFormatted": "20:51", "sta": null, "bs": "1", "tc": "0", "mt": "0", "ro": "3", "rd": "2", "rt": "5", "rf": "2", "to": "2", "st": "1", "ind": null, "pllss": "6", "val": "16", "assist": "1", "reb": "5", "pf": "4", "pts": "15", "inn": "1", "captain": "1", "id": "2650871", "no": "28", "name": "R. DIAS MARQUES LISBOA SANTOS", "logo": "https://imagenes.feb.es/foto.aspx?c=2650871"}, {"p1m": "0", "p1a": "0", "p1p": "0,0", "p2m": "1", "p2a": "2", "p2p": "50,0", "p3m": "0", "p3a": "0", "p3p": "0,0", "fgm": "1", "fga": "2", "fgp": "50,0", "min": "798", "minFormatted": "13:18", "sta": null, "bs": "1", "tc": "1", "mt": "0", "ro": "1", "rd": "3", "rt": "4", "rf": "0", "to": "1", "st": "1", "ind": null, "pllss": "0", "val": "4", "assist": "0", "reb": "4", "pf": "2", "pts": "2", "inn": "1", "captain": "0", "id": "2654188", "no": "35", "name": "R. GILL", "logo": "https://imagenes.feb.es/foto.aspx?c=2654188"}, {"p1m": "0", "p1a": "2", "p1p": "0,0", "p2m": "3", "p2a": "3", "p2p": "100,0", "p3m": "0", "p3a": "1", "p3p": "0,0", "fgm": "3", "fga": "4", "fgp": "75,0", "min": "905", "minFormatted": "15:05", "sta": null, "bs": "2", "tc": "0", "mt": "1", "ro": "2", "rd": "2", "rt": "4", "rf": "2", "to": "2", "st": "1", "ind": null, "pllss": "11", "val": "7", "assist": "1", "reb": "4", "pf": "4", "pts": "6", "inn": "1", "captain": "0", "id": "2819335", "no": "41", "name": "C. JÜRGENS", "logo": "https://imagenes.feb.es/foto.aspx?c=2819335"}], "id": "981493", "name": "CLUB OURENSE BALONCESTO", "logo": "https://imagenes.feb.es/imagen.aspx?i=981493&ti=1", "teamCode": "32000100", "clubCode": "320001"}, {"TOTAL": {"p1m": "21", "p1a": "28", "p1p": "75,0", "p2m": "16", "p2a": "31", "p2p": "51,6", "p3m": "9", "p3a": "31", "p3p": "29,0", "fgm": "25", "fga": "62", "fgp": "40,3", "assist": "12", "bs": "1", "tc": "5", "mt": "0", "ro": "12", "rd": "13", "rt": "25", "pf": "23", "rf": "23", "to": "12", "st": "7", "fastb": null, "ptsto": null, "secpts": null, "bench": null, "paint": null, "min": "12000", "minFormatted": "200:00", "val": "69", "pts": "80", "fouls": "23", "id": "981300", "name": "HESTIA MENORCA", "logo": "https://imagenes.feb.es/imagen.aspx?i=981300&ti=1", "teamCode": "07033323", "clubCode": "070333"}, "TEAMACTIONS": {"p1m": null, "p1a": null, "p1p": "0,0", "p2m": null, "p2a": null, "p2p": "0,0", "p3m": null, "p3a": null, "p3p": "0,0", "fgm": "0", "fga": "0", "fgp": "0,0", "assist": null, "bs": null, "tc": null, "mt": null, "ro": "12", "rd": "13", "rt": "25", "pf": "23", "rf": "23", "to": "12", "st": "7", "fastb": null, "ptsto": null, "secpts": null, "bench": null, "paint": null, "min": null, "minFormatted": "0:00", "val": null, "pts": null, "fouls": "23", "id": "981300", "name": "HESTIA MENORCA", "logo": "https://imagenes.feb.es/imagen.aspx?i=981300&ti=1", "teamCode": "07033323", "clubCode": "070333"}, "PLAYER": [{"p1m": "0", "p1a": "0", "p1p": "0,0", "p2m": "0", "p2a": "0", "p2p": "0,0", "p3m": "0", "p3a": "0", "p3p": "0,0", "fgm": "0", "fga": "0", "fgp": "0,0", "min": "0", "minFormatted": "00:00", "sta": null, "bs": "0", "tc": "0", "mt": "0", "ro": "0", "rd": "0", "rt": "0", "rf": "0", "to": "0", "st": "0", "ind": null, "pllss": "0", "val": "0", "assist": "0", "reb": "0", "pf": "0", "pts": "0", "inn": "0", "captain": "0", "id": "1715117", "no": "00", "name": "E. VICEDO AYALA", "logo": "https://imagenes.feb.es/foto.aspx?c=1715117"}, {"p1m": "5", "p1a": "7", "p1p": "71,4", "p2m": "0", "p2a": "2", "p2p": "0,0", "p3m": "3", "p3a": "8", "p3p": "37,5", "fgm": "3", "fga": "10", "fgp": "30,0", "min": "1406", "minFormatted": "23:26", "sta": null, "bs": "0", "tc": "0", "mt": "0", "ro": "0", "rd": "0", "rt": "0", "rf": "5", "to": "2", "st": "0", "ind": null, "pllss": "1", "val": "8", "assist": "2", "reb": "0", "pf": "2", "pts": "14", "inn": "0", "captain": "0", "id": "2785180", "no": "1", "name": "J. CONE", "logo": "https://imagenes.feb.es/foto.aspx?c=2785180"}, {"p1m": "0", "p1a": "0", "p1p": "0,0", "p2m": "0", "p2a": "2", "p2p": "0,0", "p3m": "0", "p3a": "0", "p3p": "0,0", "fgm": "0", "fga": "2", "fgp": "0,0", "min": "546", "minFormatted": "09:06", "sta": null, "bs": "0", "tc": "1", "mt": "0", "ro": "1", "rd": "1", "rt": "2", "rf": "0", "to": "0", "st": "0", "ind": null, "pllss": "4", "val": "-3", "assist": "0", "reb": "2", "pf": "3", "pts": "0", "inn": "1", "captain": "0", "id": "2820270", "no": "3", "name": "N. GALETTE", "logo": "https://imagenes.feb.es/foto.aspx?c=2820270"}, {"p1m": "0", "p1a": "0", "p1p": "0,0", "p2m": "0", "p2a": "0", "p2p": "0,0", "p3m": "0", "p3a": "0", "p3p": "0,0", "fgm": "0", "fga": "0", "fgp": "0,0", "min": "99", "minFormatted": "01:39", "sta": null, "bs": "0", "tc": "0", "mt": "0", "ro": "0", "rd": "0", "rt": "0", "rf": "0", "to": "0", "st": "0", "ind": null, "pllss": "-2", "val": "-1", "assist": "0", "reb": "0", "pf": "1", "pts": "0", "inn": "1", "captain": "0", "id": "1496030", "no": "7", "name": "P. FIGUERAS LOPEZ", "logo": "https://imagenes.feb.es/foto.aspx?c=1496030"}, {"p1m": "0", "p1a": "0", "p1p": "0,0", "p2m": "0", "p2a": "0", "p2p": "0,0", "p3m": "0", "p3a": "0", "p3p": "0,0", "fgm": "0", "fga": "0", "fgp": "0,0", "min": "1086", "minFormatted": "18:06", "sta": null, "bs": "0", "tc": "0", "mt": "0", "ro": "1", "rd": "3", "rt": "4", "rf": "0", "to": "1", "st": "0", "ind": null, "pllss": "-13", "val": "0", "assist": "1", "reb": "4", "pf": "4", "pts": "0", "inn": "0", "captain": "0", "id": "2662856", "no": "8", "name": "F. SCHOTT", "logo": "https://imagenes.feb.es/foto.aspx?c=2662856"}, {"p1m": "10", "p1a": "10", "p1p": "100,0", "p2m": "7", "p2a": "13", "p2p": "53,8", "p3m": "4", "p3a": "12", "p3p": "33,3", "fgm": "11", "fga": "25", "fgp": "44,0", "min": "2096", "minFormatted": "34:56", "sta": null, "bs": "0", "tc": "2", "mt": "0", "ro": "1", "rd": "1", "rt": "2", "rf": "7", "to": "2", "st": "3", "ind": null, "pllss": "1", "val": "36", "assist": "5", "reb": "2", "pf": "1", "pts": "36", "inn": "1", "captain": "0", "id": "2650859", "no": "11", "name": "S. LITTLESON", "logo": "https://imagenes.feb.es/foto.aspx?c=2650859"}, {"p1m": "1", "p1a": "1", "p1p": "100,0", "p2m": "4", "p2a": "4", "p2p": "100,0", "p3m": "2", "p3a": "4", "p3p": "50,0", "fgm": "6", "fga": "8", "fgp": "75,0", "min": "1263", "minFormatted": "21:03", "sta": null, "bs": "0", "tc": "0", "mt": "0", "ro": "0", "rd": "0", "rt": "0", "rf": "2", "to": "1", "st": "0", "ind": null, "pllss": "5", "val": "10", "assist": "0", "reb": "0", "pf": "4", "pts": "15", "inn": "0", "captain": "0", "id": "1938697", "no": "13", "name": "J. LOBO MARTORELL", "logo": "https://imagenes.feb.es/foto.aspx?c=1938697"}, {"p1m": "0", "p1a": "0", "p1p": "0,0", "p2m": "0", "p2a": "1", "p2p": "0,0", "p3m": "0", "p3a": "1", "p3p": "0,0", "fgm": "0", "fga": "2", "fgp": "0,0", "min": "523", "minFormatted": "08:43", "sta": null, "bs": "0", "tc": "1", "mt": "0", "ro": "0", "rd": "0", "rt": "0", "rf": "0", "to": "1", "st": "1", "ind": null, "pllss": "-12", "val": "-2", "assist": "1", "reb": "0", "pf": "1", "pts": "0", "inn": "0", "captain": "0", "id": "1784407", "no": "15", "name": "P. MOLINS CALDERON", "logo": "https://imagenes.feb.es/foto.aspx?c=1784407"}, {"p1m": "1", "p1a": "2", "p1p": "50,0", "p2m": "3", "p2a": "7", "p2p": "42,9", "p3m": "0", "p3a": "3", "p3p": "0,0", "fgm": "3", "fga": "10", "fgp": "30,0", "min": "2160", "minFormatted": "36:00", "sta": null, "bs": "0", "tc": "1", "mt": "0", "ro": "1", "rd": "1", "rt": "2", "rf": "2", "to": "2", "st": "2", "ind": null, "pllss": "7", "val": "2", "assist": "1", "reb": "2", "pf": "2", "pts": "7", "inn": "1", "captain": "0", "id": "2702840", "no": "23", "name": "E. WEMBI", "logo": "https://imagenes.feb.es/foto.aspx?c=2702840"}, {"p1m": "3", "p1a": "6", "p1p": "50,0", "p2m": "0", "p2a": "0", "p2p": "0,0", "p3m": "0", "p3a": "3", "p3p": "0,0", "fgm": "0", "fga": "3", "fgp": "0,0", "min": "1813", "minFormatted": "30:13", "sta": null, "bs": "0", "tc": "0", "mt": "0", "ro": "4", "rd": "3", "rt": "7", "rf": "6", "to": "0", "st": "1", "ind": null, "pllss": "-5", "val": "12", "assist": "2", "reb": "7", "pf": "1", "pts": "3", "inn": "1", "captain": "1", "id": "1875914", "no": "55", "name": "A. SOLA IDDRISU", "logo": "https://imagenes.feb.es/foto.aspx?c=1875914"}, {"p1m": "1", "p1a": "2", "p1p": "50,0", "p2m": "2", "p2a": "2", "p2p": "100,0", "p3m": "0", "p3a": "0", "p3p": "0,0", "fgm": "2", "fga": "2", "fgp": "100,0", "min": "1008", "minFormatted": "16:48", "sta": null, "bs": "1", "tc": "0", "mt": "0", "ro": "4", "rd": "4", "rt": "8", "rf": "1", "to": "3", "st": "0", "ind": null, "pllss": "-6", "val": "7", "assist": "0", "reb": "8", "pf": "4", "pts": "5", "inn": "0", "captain": "0", "id": "1382456", "no": "77", "name": "V. ARTEAGA GONZALEZ", "logo": "https://imagenes.feb.es/foto.aspx?c=1382456"}], "id": "981300", "name": "HESTIA MENORCA", "logo": "https://imagenes.feb.es/imagen.aspx?i=981300&ti=1", "teamCode": "07033323", "clubCode": "070333"}]}, "SHOTCHART": null, "RANKING": null}